CHANGES.rst
MANIFEST.in
README.rst
setup.py
src/bda/__init__.py
src/bda.basen.egg-info/PKG-INFO
src/bda.basen.egg-info/SOURCES.txt
src/bda.basen.egg-info/dependency_links.txt
src/bda.basen.egg-info/namespace_packages.txt
src/bda.basen.egg-info/not-zip-safe
src/bda.basen.egg-info/requires.txt
src/bda.basen.egg-info/top_level.txt
src/bda/basen/__init__.py
src/bda/basen/basen.py
src/bda/basen/convert.py
src/bda/basen/tests.py
src/bda/basen/tests.rst